bc_edu_sdk-0.2.2.dist-info/METADATA
bc_edu_sdk-0.2.2.dist-info/WHEEL
bc_edu_sdk-0.2.2.dist-info/licenses/LICENSE
bc_edu_sdk/main_mod.pyi
bc_edu_sdk/main_mod.abi3.so
bc_edu_sdk-0.2.2.dist-info/RECORD
