Metadata-Version: 2.4
Name: bc_edu_sdk
Version: 0.2.2
Classifier: Programming Language :: Rust
Classifier: Programming Language :: Python :: Implementation :: CPython
Classifier: Programming Language :: Python :: Implementation :: PyPy
License-File: LICENSE
Summary: BrainCo EDU Serial SDK for educational device integration
Author: BrainCo, Yongle-Fu
License: 	
Requires-Python: >=3.8
Project-URL: Source Code, https://github.com/BrainCoTech/bc-edu-sdk
